readet/__init__.py
readet/bots/__init__.py
readet/bots/agents.py
readet/bots/chat_tools.py
readet/bots/components.py
readet/bots/multi_agents.py
readet/bots/prebuilt.py
readet/core/__init__.py
readet/core/chains.py
readet/core/knowledge_graphs.py
readet/core/rags.py
readet/core/retrievers.py
readet/core/summarizers.py
readet/core/tools.py
readet/utils/__init__.py
readet/utils/docs.py
readet/utils/io.py
readet/utils/models.py
readet/utils/save_load.py
readet/utils/schemas.py
readet-0.1.1.dist-info/LICENSE.md
readet-0.1.1.dist-info/METADATA
readet-0.1.1.dist-info/WHEEL
readet-0.1.1.dist-info/top_level.txt
readet-0.1.1.dist-info/RECORD
