Metadata-Version: 2.1
Name: readet
Version: 0.1.1
Summary: This patch includes several improvement to RAGs, summarizers, downloders and retrievers; plus compatibility for windows installation
Author-email: Hamed Haddadi <haddadi.h81@gmail.com>
License: Copyright (c) 2018 The Python Packaging Authority
Project-URL: Homepage, https://github.com/HamedHaddadi/readet
Requires-Python: >=3.10
License-File: LICENSE.md
Requires-Dist: accelerate==1.2.0
Requires-Dist: aiohappyeyeballs==2.4.4
Requires-Dist: aiohttp==3.11.10
Requires-Dist: aiosignal==1.3.1
Requires-Dist: annotated-types==0.7.0
Requires-Dist: anthropic==0.40.0
Requires-Dist: anyio==4.7.0
Requires-Dist: appnope==0.1.4
Requires-Dist: argon2-cffi==23.1.0
Requires-Dist: argon2-cffi-bindings==21.2.0
Requires-Dist: arrow==1.3.0
Requires-Dist: arxiv==2.1.3
Requires-Dist: asgiref==3.8.1
Requires-Dist: asttokens==3.0.0
Requires-Dist: async-lru==2.0.4
Requires-Dist: async-timeout==4.0.3
Requires-Dist: attrs==24.2.0
Requires-Dist: babel==2.16.0
Requires-Dist: backoff==2.2.1
Requires-Dist: bcrypt==4.2.1
Requires-Dist: beautifulsoup4==4.12.3
Requires-Dist: bleach==6.2.0
Requires-Dist: blinker==1.9.0
Requires-Dist: Bottleneck==1.4.2
Requires-Dist: Brotli==1.1.0
Requires-Dist: build==1.2.2.post1
Requires-Dist: cachetools==5.5.0
Requires-Dist: certifi==2024.8.30
Requires-Dist: cffi==1.17.1
Requires-Dist: charset-normalizer==3.4.0
Requires-Dist: chroma-hnswlib==0.7.6
Requires-Dist: chromadb==0.5.23
Requires-Dist: click==8.1.7
Requires-Dist: colorama==0.4.6
Requires-Dist: coloredlogs==15.0.1
Requires-Dist: comm==0.2.2
Requires-Dist: contourpy==1.3.1
Requires-Dist: cryptography==44.0.0
Requires-Dist: cycler==0.12.1
Requires-Dist: dataclasses-json==0.6.7
Requires-Dist: datasets==3.2.0
Requires-Dist: debugpy==1.8.10
Requires-Dist: decorator==5.1.1
Requires-Dist: defusedxml==0.7.1
Requires-Dist: Deprecated==1.2.15
Requires-Dist: dill==0.3.8
Requires-Dist: distro==1.9.0
Requires-Dist: durationpy==0.9
Requires-Dist: exceptiongroup==1.2.2
Requires-Dist: executing==2.1.0
Requires-Dist: faiss-cpu==1.9.0.post1
Requires-Dist: fastapi==0.115.6
Requires-Dist: fastjsonschema==2.21.1
Requires-Dist: feedparser==6.0.11
Requires-Dist: filelock==3.16.1
Requires-Dist: flatbuffers==24.3.25
Requires-Dist: fonttools==4.55.3
Requires-Dist: fqdn==1.5.1
Requires-Dist: frozenlist==1.5.0
Requires-Dist: fsspec==2024.9.0
Requires-Dist: gmpy2==2.2.1
Requires-Dist: google-auth==2.36.0
Requires-Dist: googleapis-common-protos==1.66.0
Requires-Dist: greenlet==3.1.1
Requires-Dist: grpcio==1.68.1
Requires-Dist: h11==0.14.0
Requires-Dist: httpcore==1.0.7
Requires-Dist: httptools==0.6.4
Requires-Dist: httpx==0.28.1
Requires-Dist: httpx-sse==0.4.0
Requires-Dist: huggingface-hub==0.26.5
Requires-Dist: humanfriendly==10.0
Requires-Dist: idna==3.10
Requires-Dist: importlib_metadata==8.5.0
Requires-Dist: importlib_resources==6.4.5
Requires-Dist: ipykernel==6.29.5
Requires-Dist: ipython==8.30.0
Requires-Dist: ipywidgets==8.1.5
Requires-Dist: isoduration==20.11.0
Requires-Dist: jedi==0.19.2
Requires-Dist: Jinja2==3.1.4
Requires-Dist: jiter==0.8.2
Requires-Dist: joblib==1.4.2
Requires-Dist: json5==0.10.0
Requires-Dist: jsonpatch==1.33
Requires-Dist: jsonpointer==3.0.0
Requires-Dist: jsonschema==4.23.0
Requires-Dist: jsonschema-specifications==2024.10.1
Requires-Dist: jupyter==1.1.1
Requires-Dist: jupyter-console==6.6.3
Requires-Dist: jupyter-events==0.10.0
Requires-Dist: jupyter-lsp==2.2.5
Requires-Dist: jupyter_client==8.6.3
Requires-Dist: jupyter_core==5.7.2
Requires-Dist: jupyter_server==2.14.2
Requires-Dist: jupyter_server_terminals==0.5.3
Requires-Dist: jupyterlab==4.3.3
Requires-Dist: jupyterlab_pygments==0.3.0
Requires-Dist: jupyterlab_server==2.27.3
Requires-Dist: jupyterlab_widgets==3.0.13
Requires-Dist: kiwisolver==1.4.7
Requires-Dist: kubernetes==31.0.0
Requires-Dist: langchain==0.3.11
Requires-Dist: langchain-anthropic==0.3.0
Requires-Dist: langchain-chroma==0.1.4
Requires-Dist: langchain-community==0.3.11
Requires-Dist: langchain-core==0.3.24
Requires-Dist: langchain-experimental==0.3.3
Requires-Dist: langchain-huggingface==0.1.2
Requires-Dist: langchain-openai==0.2.12
Requires-Dist: langchain-text-splitters==0.3.2
Requires-Dist: langchainhub==0.1.21
Requires-Dist: langgraph==0.2.58
Requires-Dist: langgraph-checkpoint==2.0.8
Requires-Dist: langgraph-sdk==0.1.43
Requires-Dist: langsmith==0.2.2
Requires-Dist: markdown-it-py==3.0.0
Requires-Dist: MarkupSafe==3.0.2
Requires-Dist: marshmallow==3.23.1
Requires-Dist: matplotlib==3.9.3
Requires-Dist: matplotlib-inline==0.1.7
Requires-Dist: mdurl==0.1.2
Requires-Dist: mistune==3.0.2
Requires-Dist: mmh3==5.0.1
Requires-Dist: monotonic==1.6
Requires-Dist: mpl_point_clicker==0.4.1
Requires-Dist: mpmath==1.3.0
Requires-Dist: msgpack==1.1.0
Requires-Dist: multidict==6.1.0
Requires-Dist: multiprocess==0.70.16
Requires-Dist: mypy-extensions==1.0.0
Requires-Dist: nbclient==0.10.1
Requires-Dist: nbconvert==7.16.4
Requires-Dist: nbformat==5.10.4
Requires-Dist: neo4j==5.27.0
Requires-Dist: nest-asyncio==1.6.0
Requires-Dist: networkx==3.4.2
Requires-Dist: nltk==3.9.1
Requires-Dist: notebook==7.3.1
Requires-Dist: notebook_shim==0.2.4
Requires-Dist: numexpr==2.10.2
Requires-Dist: numpy==1.26.4
Requires-Dist: oauthlib==3.2.2
Requires-Dist: onnxruntime==1.20.1
Requires-Dist: openai==1.57.2
Requires-Dist: opencv-python==4.10.0.84
Requires-Dist: opentelemetry-api==1.28.2
Requires-Dist: opentelemetry-exporter-otlp-proto-common==1.28.2
Requires-Dist: opentelemetry-exporter-otlp-proto-grpc==1.28.2
Requires-Dist: opentelemetry-instrumentation==0.49b2
Requires-Dist: opentelemetry-instrumentation-asgi==0.49b2
Requires-Dist: opentelemetry-instrumentation-fastapi==0.49b2
Requires-Dist: opentelemetry-proto==1.28.2
Requires-Dist: opentelemetry-sdk==1.28.2
Requires-Dist: opentelemetry-semantic-conventions==0.49b2
Requires-Dist: opentelemetry-util-http==0.49b2
Requires-Dist: orjson==3.10.12
Requires-Dist: overrides==7.7.0
Requires-Dist: packaging==24.2
Requires-Dist: pandas==2.2.3
Requires-Dist: pandocfilters==1.5.1
Requires-Dist: parso==0.8.4
Requires-Dist: pdfminer.six==20231228
Requires-Dist: pdfplumber==0.11.4
Requires-Dist: pexpect==4.9.0
Requires-Dist: pillow==11.0.0
Requires-Dist: pkgutil_resolve_name==1.3.10
Requires-Dist: platformdirs==4.3.6
Requires-Dist: plotly==5.24.1
Requires-Dist: ply==3.11
Requires-Dist: posthog==3.7.4
Requires-Dist: prometheus_client==0.21.1
Requires-Dist: prompt_toolkit==3.0.48
Requires-Dist: propcache==0.2.1
Requires-Dist: protobuf==5.29.1
Requires-Dist: psutil==6.1.0
Requires-Dist: ptyprocess==0.7.0
Requires-Dist: pulsar-client==3.5.0
Requires-Dist: pure_eval==0.2.3
Requires-Dist: pyarrow==18.1.0
Requires-Dist: pyasn1==0.6.1
Requires-Dist: pyasn1_modules==0.4.1
Requires-Dist: pyclipper==1.3.0.post6
Requires-Dist: pycparser==2.22
Requires-Dist: pydantic==2.10.3
Requires-Dist: pydantic-settings==2.6.1
Requires-Dist: pydantic_core==2.27.1
Requires-Dist: Pygments==2.18.0
Requires-Dist: PyJWT==2.10.1
Requires-Dist: PyMuPDF==1.25.0
Requires-Dist: PyMuPDFb==1.24.10
Requires-Dist: pyOpenSSL==24.3.0
Requires-Dist: pyparsing==3.2.0
Requires-Dist: pypdf==5.1.0
Requires-Dist: pypdfium2==4.30.0
Requires-Dist: PyPika==0.48.9
Requires-Dist: pyproject_hooks==1.2.0
Requires-Dist: PyQt5
Requires-Dist: PyQt5-Qt5
Requires-Dist: PyQt5_sip
Requires-Dist: PySocks==1.7.1
Requires-Dist: python-dateutil==2.9.0.post0
Requires-Dist: python-dotenv==1.0.1
Requires-Dist: python-json-logger==2.0.7
Requires-Dist: pytz==2024.2
Requires-Dist: PyYAML==6.0.2
Requires-Dist: pyzmq==26.2.0
Requires-Dist: qtconsole==5.6.1
Requires-Dist: QtPy==2.4.2
Requires-Dist: rake-nltk==1.0.6
Requires-Dist: rank-bm25==0.2.2
Requires-Dist: rapidocr-onnxruntime==1.4.2
Requires-Dist: referencing==0.35.1
Requires-Dist: regex==2024.11.6
Requires-Dist: requests==2.32.3
Requires-Dist: requests-oauthlib==2.0.0
Requires-Dist: requests-toolbelt==1.0.0
Requires-Dist: rfc3339-validator==0.1.4
Requires-Dist: rfc3986-validator==0.1.1
Requires-Dist: rich==13.9.4
Requires-Dist: rpds-py==0.22.3
Requires-Dist: rsa==4.9
Requires-Dist: safetensors==0.4.5
Requires-Dist: scikit-learn==1.6.0
Requires-Dist: scipy==1.14.1
Requires-Dist: semanticscholar==0.9.0
Requires-Dist: Send2Trash==1.8.3
Requires-Dist: sentence-transformers==3.3.1
Requires-Dist: sentencepiece==0.2.0
Requires-Dist: serpapi==0.1.5
Requires-Dist: sgmllib3k==1.0.0
Requires-Dist: shapely==2.0.6
Requires-Dist: shellingham==1.5.4
Requires-Dist: sip==6.9.0
Requires-Dist: six==1.17.0
Requires-Dist: sniffio==1.3.1
Requires-Dist: soupsieve==2.6
Requires-Dist: SQLAlchemy==2.0.36
Requires-Dist: stack-data==0.6.3
Requires-Dist: starlette==0.41.3
Requires-Dist: sympy==1.13.1
Requires-Dist: tavily-python==0.5.0
Requires-Dist: tenacity==9.0.0
Requires-Dist: terminado==0.18.1
Requires-Dist: text-generation==0.7.0
Requires-Dist: threadpoolctl==3.5.0
Requires-Dist: tiktoken==0.8.0
Requires-Dist: tinycss2==1.4.0
Requires-Dist: tokenizers==0.20.3
Requires-Dist: tomli==2.2.1
Requires-Dist: torch==2.5.1
Requires-Dist: torchvision==0.20.1
Requires-Dist: tornado==6.4.2
Requires-Dist: tqdm==4.67.1
Requires-Dist: traitlets==5.14.3
Requires-Dist: transformers==4.46.3
Requires-Dist: typer==0.15.1
Requires-Dist: types-python-dateutil==2.9.0.20241206
Requires-Dist: types-requests==2.32.0.20241016
Requires-Dist: types-urllib3==1.26.25.14
Requires-Dist: typing-inspect==0.9.0
Requires-Dist: typing_extensions==4.12.2
Requires-Dist: tzdata==2024.2
Requires-Dist: unicodedata2==15.1.0
Requires-Dist: uri-template==1.3.0
Requires-Dist: urllib3==2.2.3
Requires-Dist: uvicorn==0.32.1
Requires-Dist: watchfiles==1.0.3
Requires-Dist: wcwidth==0.2.13
Requires-Dist: webcolors==24.11.1
Requires-Dist: webencodings==0.5.1
Requires-Dist: websocket-client==1.8.0
Requires-Dist: websockets==14.1
Requires-Dist: widgetsnbextension==4.0.13
Requires-Dist: wikipedia==1.4.0
Requires-Dist: wrapt==1.17.0
Requires-Dist: xxhash==3.5.0
Requires-Dist: yarl==1.18.3
Requires-Dist: zipp==3.21.0
